redis_pubsub_dict
