Metadata-Version: 1.1
Name: redis-pubsub-dict
Version: 0.0.2
Summary: A python class for using redis, or other key value stores, and caching the values for read heavy workloads
Home-page: https://github.com/Richard-Mathie/py-redis-pubsub-dict
Author: Richard Mathie
Author-email: richard.mathie@cantab.net
License: GNU GPLv2
Platform: any
Classifier: Environment :: Web Environment
Classifier: Intended Audience :: Developers
Classifier: License :: OSI Approved :: BSD License
Classifier: Operating System :: OS Independent
Classifier: Programming Language :: Python
Classifier: Programming Language :: Python :: 2
Classifier: Programming Language :: Python :: 2.6
Classifier: Programming Language :: Python :: 2.7
